human_parsing/__init__.py
human_parsing/segmentation.py
human_parsing-0.0.4.dist-info/LICENSE
human_parsing-0.0.4.dist-info/METADATA
human_parsing-0.0.4.dist-info/WHEEL
human_parsing-0.0.4.dist-info/top_level.txt
human_parsing-0.0.4.dist-info/RECORD
